aict_tools/__init__.py
aict_tools/apply.py
aict_tools/configuration.py
aict_tools/cta_helpers.py
aict_tools/feature_generation.py
aict_tools/features.py
aict_tools/io.py
aict_tools/logging.py
aict_tools/onnx.py
aict_tools/parallel.py
aict_tools/plotting.py
aict_tools/pmml.py
aict_tools/preprocessing.py
aict_tools/scripts/__init__.py
aict_tools/scripts/apply_cuts.py
aict_tools/scripts/apply_disp_regressor.py
aict_tools/scripts/apply_dxdy_regressor.py
aict_tools/scripts/apply_energy_regressor.py
aict_tools/scripts/apply_separation_model.py
aict_tools/scripts/convert_pandas2h5py.py
aict_tools/scripts/fact_to_dl3.py
aict_tools/scripts/plot_disp_performance.py
aict_tools/scripts/plot_dxdy_performance.py
aict_tools/scripts/plot_regressor_performance.py
aict_tools/scripts/plot_separator_performance.py
aict_tools/scripts/split_data.py
aict_tools/scripts/train_disp_regressor.py
aict_tools/scripts/train_dxdy_regressor.py
aict_tools/scripts/train_energy_regressor.py
aict_tools/scripts/train_separation_model.py
aict_tools-0.27.1.dist-info/LICENSE
aict_tools-0.27.1.dist-info/METADATA
aict_tools-0.27.1.dist-info/WHEEL
aict_tools-0.27.1.dist-info/entry_points.txt
aict_tools-0.27.1.dist-info/top_level.txt
aict_tools-0.27.1.dist-info/RECORD
