Metadata-Version: 2.1
Name: aict-tools
Version: 0.27.1
Summary: Artificial Intelligence for Imaging Atmospheric Cherenkov Telescopes
Home-page: https://github.com/fact-project/aict-tools
Author: Kai Brügge, Maximilian Nöthe, Jens Buss
Author-email: kai.bruegge@tu-dortmund.de
License: MIT
Platform: UNKNOWN
Classifier: Development Status :: 4 - Beta
Classifier: Intended Audience :: Science/Research
Classifier: License :: OSI Approved :: MIT License
Classifier: Natural Language :: English
Classifier: Operating System :: OS Independent
Classifier: Programming Language :: Python
Classifier: Programming Language :: Python :: 3.7
Classifier: Programming Language :: Python :: 3.8
Classifier: Programming Language :: Python :: 3 :: Only
Classifier: Topic :: Scientific/Engineering :: Astronomy
Classifier: Topic :: Scientific/Engineering :: Physics
Classifier: Topic :: Scientific/Engineering :: Artificial Intelligence
Classifier: Topic :: Scientific/Engineering :: Information Analysis
Requires-Python: >=3.7
Requires-Dist: astropy (~=4.2)
Requires-Dist: click
Requires-Dist: h5py
Requires-Dist: joblib
Requires-Dist: matplotlib (>=2.0)
Requires-Dist: numexpr
Requires-Dist: numpy
Requires-Dist: pandas
Requires-Dist: pyfact (>=0.16.0)
Requires-Dist: python-dateutil
Requires-Dist: pytz
Requires-Dist: ruamel.yaml (>=0.15.0)
Requires-Dist: scikit-learn (>=0.21.0)
Requires-Dist: tables (>=3tqdm)
Provides-Extra: all
Requires-Dist: skl2onnx ; extra == 'all'
Requires-Dist: pytest-cov ; extra == 'all'
Requires-Dist: pytest ; extra == 'all'
Requires-Dist: sklearn2pmml (>=0.66) ; extra == 'all'
Requires-Dist: onnxruntime (~=1.0) ; extra == 'all'
Requires-Dist: pytest-runner ; extra == 'all'
Requires-Dist: onnxmltools ; extra == 'all'
Requires-Dist: ctapipe ; extra == 'all'
Requires-Dist: jpmml-evaluator (>=0.2.2) ; extra == 'all'
Provides-Extra: cta
Requires-Dist: ctapipe ; extra == 'cta'
Provides-Extra: onnx
Requires-Dist: skl2onnx ; extra == 'onnx'
Requires-Dist: onnxmltools ; extra == 'onnx'
Requires-Dist: onnxruntime (~=1.0) ; extra == 'onnx'
Provides-Extra: pmml
Requires-Dist: sklearn2pmml (>=0.66) ; extra == 'pmml'
Requires-Dist: jpmml-evaluator (>=0.2.2) ; extra == 'pmml'
Provides-Extra: tests
Requires-Dist: pytest ; extra == 'tests'
Requires-Dist: pytest-runner ; extra == 'tests'
Requires-Dist: pytest-cov ; extra == 'tests'
